Metadata-Version: 1.0
Name: sLIntell
Version: 1.0.1
Summary: This is a package which can speak and listen to your commands. Developed for personal use only. Copyright to Siddh Rathod
Home-page: UNKNOWN
Author: Siddh Rathod
Author-email: siddhrathod1@gmail.com
License: MIT
Keywords: speak tool,listen tool
Platform: UNKNOWN
